<annotation>
	<folder>JPEGImages</folder>
	<filename>fish_000004750001_00509.png</filename>
	<path>D:\jingwei\GraduateStudent\神经网络\pytorch\VOC\JPEGImages\fish_000004750001_00509.png</path>
	<source>
		<database>Unknown</database>
	</source>
	<size>
		<width>131</width>
		<height>175</height>
		<depth>3</depth>
	</size>
	<segmented>0</segmented>
	<object>
		<name>fish</name>
		<pose>Unspecified</pose>
		<truncated>1</truncated>
		<difficult>0</difficult>
		<bndbox>
			<xmin>108</xmin>
			<ymin>61</ymin>
			<xmax>131</xmax>
			<ymax>87</ymax>
		</bndbox>
	</object>
	<object>
		<name>fish</name>
		<pose>Unspecified</pose>
		<truncated>0</truncated>
		<difficult>0</difficult>
		<bndbox>
			<xmin>36</xmin>
			<ymin>44</ymin>
			<xmax>88</xmax>
			<ymax>130</ymax>
		</bndbox>
	</object>
	<object>
		<name>fish</name>
		<pose>Unspecified</pose>
		<truncated>0</truncated>
		<difficult>0</difficult>
		<bndbox>
			<xmin>79</xmin>
			<ymin>116</ymin>
			<xmax>89</xmax>
			<ymax>128</ymax>
		</bndbox>
	</object>
	<object>
		<name>fish</name>
		<pose>Unspecified</pose>
		<truncated>1</truncated>
		<difficult>0</difficult>
		<bndbox>
			<xmin>119</xmin>
			<ymin>98</ymin>
			<xmax>131</xmax>
			<ymax>120</ymax>
		</bndbox>
	</object>
</annotation>
